odoo/addons/website_sale_order_cancel/README.rst
odoo/addons/website_sale_order_cancel/__init__.py
odoo/addons/website_sale_order_cancel/__manifest__.py
odoo/addons/website_sale_order_cancel/controllers/__init__.py
odoo/addons/website_sale_order_cancel/controllers/main.py
odoo/addons/website_sale_order_cancel/i18n/ca.po
odoo/addons/website_sale_order_cancel/i18n/es.po
odoo/addons/website_sale_order_cancel/i18n/website_sale_order_cancel.pot
odoo/addons/website_sale_order_cancel/models/__init__.py
odoo/addons/website_sale_order_cancel/models/res_config_settings.py
odoo/addons/website_sale_order_cancel/models/sale_order.py
odoo/addons/website_sale_order_cancel/readme/CONTRIBUTORS.rst
odoo/addons/website_sale_order_cancel/readme/DESCRIPTION.rst
odoo/addons/website_sale_order_cancel/readme/USAGE.rst
odoo/addons/website_sale_order_cancel/static/description/icon.png
odoo/addons/website_sale_order_cancel/static/description/index.html
odoo/addons/website_sale_order_cancel/static/src/js/website_sale_order_cancel.js
odoo/addons/website_sale_order_cancel/static/tests/tours/cancel_order_tour.js
odoo/addons/website_sale_order_cancel/tests/__init__.py
odoo/addons/website_sale_order_cancel/tests/test_sale_order_cancel_tour.py
odoo/addons/website_sale_order_cancel/views/res_config_settings_views.xml
odoo/addons/website_sale_order_cancel/views/templates.xml
odoo_addon_website_sale_order_cancel-15.0.1.0.1.dist-info/METADATA
odoo_addon_website_sale_order_cancel-15.0.1.0.1.dist-info/WHEEL
odoo_addon_website_sale_order_cancel-15.0.1.0.1.dist-info/top_level.txt
odoo_addon_website_sale_order_cancel-15.0.1.0.1.dist-info/RECORD
